hawkpy/__init__.py
hawkpy/crypto.py
hawkpy/exploit.py
hawkpy/password_cracker.py
hawkpy/scanner.py
hawkpy/utils.py
hawkpy-1.0.0.dist-info/METADATA
hawkpy-1.0.0.dist-info/WHEEL
hawkpy-1.0.0.dist-info/top_level.txt
hawkpy-1.0.0.dist-info/RECORD
